Metadata-Version: 2.1
Name: grpc-protoc-annotations
Version: 2.16.0
Summary: Provides the missing pieces for gRPC Gateway.
Home-page: https://github.com/prosehair/grpc_protoc_annotations
Author: Prosehair
Author-email: nicolas@prosehair.com
Project-URL: Bug Tracker, https://github.com/prosehair/grpc_protoc_annotations/issues
Classifier: Programming Language :: Python :: 3
Classifier: License :: OSI Approved :: BSD License
Classifier: Operating System :: OS Independent
Requires-Python: >=3.6
License-File: LICENSE
Requires-Dist: googleapis-common-protos
